ccqppy/__init__.py
ccqppy/problem_suite.py
ccqppy/solution_spaces.py
ccqppy/solvers.py
ccqppy-0.0.0.dist-info/LICENSE
ccqppy-0.0.0.dist-info/METADATA
ccqppy-0.0.0.dist-info/WHEEL
ccqppy-0.0.0.dist-info/top_level.txt
ccqppy-0.0.0.dist-info/RECORD
